{
   "registration":
   [
      {
         "name":"Name",
         "query":"I\\'ll register you for HvZ!\nWhat is your name? Use the name you would use on homework.",
         "valid_regex":"\\D*",
         "rejection_response":"No numbers allowed in names."
      },
      {
         "name":"CPO",
         "query":"What is your CPO? This is used for player band delivery.\nIf you don\\'t have one (such as commuters), please type \"None\"",
         "valid_regex":"(?i)\\d*|none",
         "rejection_response":"I'm looking for a single number here, or None. Try again."
      },
      {
         "name":"email",
         "query":"What is your @LETU.edu email?",
         "valid_regex":"(^[a-zA-Z0-9_.+-]+@[a-zA-Z0-9-]+\\.[a-zA-Z0-9-.]+$)",
         "rejection_response":"That isn\\'t a valid email. Try again."
      },
      {
         "name":"oz_desire",
         "query":"Do you want a chance to be one of the original zombies? If chosen, you won\\'t be a human this game.\nAnswer \"yes\" or \"no\".",
         "valid_regex":"(?i)\\s*(yes|no)\\s*",
         "rejection_response":"Just need a yes or no here."
      }
   ],
   "tag_logging":
   [
      {
         "name":"Tag_Code",
         "query":"What is the tag code of the human you tagged?",
         "valid_regex":"[A-Z\\d]{6}",
         "rejection_response":"Try again! The tag code is 6 characters of numbers and capital letters. None of these: 0 o O Q I 1 D V U"
      },
      {
         "name":"Tag_Day",
         "query":"Did the tag happen \"today\" or \"yesterday\"?",
         "valid_regex":"(?i)(today)|yesterday",
         "rejection_response":"Try again. Respond with either \"today\" or \"tomorrow\""
      },
      {
         "name":"Tag_Time",
         "query":"About what time did the tag happen? Use the format 3:04pm",
         "valid_regex":"(?i)\\d{1,2}:[0-5]?[0-9]\\s?(am|pm)",
         "rejection_response":"Try again. Please use a format like 12:26pm or 7:00 am"  
      }
   ]
}